wz_uniform_crawler/__init__.py
wz_uniform_crawler-1.0.1.dist-info/LICENSE
wz_uniform_crawler-1.0.1.dist-info/METADATA
wz_uniform_crawler-1.0.1.dist-info/WHEEL
wz_uniform_crawler-1.0.1.dist-info/top_level.txt
wz_uniform_crawler-1.0.1.dist-info/RECORD
