Metadata-Version: 2.1
Name: wz-uniform-crawler
Version: 1.0.1
Summary: A simple crawler script for Uniform Map / 制服地圖 (http://uniform.wingzero.tw/)
Home-page: https://github.com/issaclin32/wz_uniform_crawler
Author: Issac Lin
Author-email: issaclin32@gmail.com
License: UNKNOWN
Platform: UNKNOWN
Classifier: Programming Language :: Python :: 3
Classifier: License :: OSI Approved :: MIT License
Classifier: Operating System :: OS Independent
Requires-Dist: beautifulsoup4
